langeval/__init__.py
langeval/consistency/__init__.py
langeval/fairness/__init__.py
langeval/integrity/__init__.py
langeval/performance/__init__.py
langeval/performance/rouge.py
langeval/performance/tests.py
langeval/robustness/__init__.py
langeval/utils/__init__.py
langtest/__init__.py
langtest/consistency/__init__.py
langtest/fairness/__init__.py
langtest/integrity/__init__.py
langtest/performance/__init__.py
langtest/performance/rouge.py
langtest/performance/tests.py
langtest/robustness/__init__.py
langtest/utils/__init__.py
langtests-0.1.dist-info/LICENSE
langtests-0.1.dist-info/METADATA
langtests-0.1.dist-info/WHEEL
langtests-0.1.dist-info/top_level.txt
langtests-0.1.dist-info/RECORD
